coloursamples/__init__.py
coloursamples/_version.py
coloursamples/cli.py
coloursamples/core.py
coloursamples/exceptions.py
coloursamples-0.1.5.dist-info/METADATA
coloursamples-0.1.5.dist-info/WHEEL
coloursamples-0.1.5.dist-info/entry_points.txt
coloursamples-0.1.5.dist-info/RECORD
