Metadata-Version: 2.4
Name: coloursamples
Version: 0.1.5
Summary: Python utility for generating JPEG images with specified dimensions and colours
Project-URL: Homepage, https://github.com/jackemcpherson/colourSamples
Project-URL: Repository, https://github.com/jackemcpherson/colourSamples
Project-URL: Bug Tracker, https://github.com/jackemcpherson/colourSamples/issues
Requires-Python: >=3.8
Requires-Dist: pillow>=10.0.0
Requires-Dist: rich>=13.0.0
Requires-Dist: typer>=0.9.0
